pycextensions/__init__.py
pycextensions/fprintf.cp39-win32.pyd
pycextensions/util.py
pycextensions-0.2.0.dist-info/LICENSE
pycextensions-0.2.0.dist-info/METADATA
pycextensions-0.2.0.dist-info/WHEEL
pycextensions-0.2.0.dist-info/top_level.txt
pycextensions-0.2.0.dist-info/RECORD
