Metadata-Version: 2.1
Name: pycextensions
Version: 0.2.0
Summary: a python c extension example
Home-page: https://github.com/shengchenyang
Author: ayuge
Author-email: ayuge@gmail.com
Classifier: Development Status :: 4 - Beta
Classifier: Programming Language :: Python :: 3.8
Classifier: Programming Language :: Python :: 3.9
Classifier: Programming Language :: Python :: 3.10
Classifier: Programming Language :: Python :: 3.11
Classifier: Programming Language :: Python :: 3.12
Classifier: Intended Audience :: Developers
Classifier: License :: OSI Approved :: MIT License
Classifier: Operating System :: MacOS
Classifier: Operating System :: POSIX :: Linux
Classifier: Operating System :: Microsoft :: Windows
Classifier: Topic :: Education
Classifier: Topic :: Software Development :: Code Generators
Classifier: Topic :: Software Development :: Libraries :: Python Modules
Classifier: Topic :: Utilities
Requires-Python: >=3.8
License-File: LICENSE
Requires-Dist: objprint (>=0.1.3)
Provides-Extra: full
Requires-Dist: rich ; extra == 'full'
Requires-Dist: orjson ; extra == 'full'
